{"black": "Kovanova,B", "white": "Zhu Chen", "winner": "White", "playedAt": "2009.10.05", "location": "Nanjing CHN", "event": "2009-10 FIDE Women's Grand Prix", "moves": "pgn1.d4 Nf6 2.c4 e6 3.Nc3 Bb4 4.Qc2 O-O 5.a3 Bxc3+ 6.Qxc3 d6 7.f3 Nh5 8.Nh3 f5\n9.Nf2 Nc6 10.b3 e5 11.d5 Ne7 12.e3 Kh8 13.Bb2 f4 14.e4 b6 15.b4 a5\n16.c5 Ng6 17.Rc1 axb4 18.axb4 bxc5 19.bxc5 Bd7 20.Ba3 Qg5 21.Rg1 Nh4\n22.c6 Bc8 23.Rb1 h6 24.Bc1 Qe7 25.Ra1 Rb8 26.Ra7 Rb6 27.Kd1 Ng6 28.Bd2 Kh7\n29.Kc2 Nf6 30.Bc4 Ne8 31.Be1 Rb8 32.Nd1 Qg5 33.Bf2 h5 34.Ra1 Ne7 35.Qa5 Qf6\n36.Ra4 g5 37.Qa7 1-0\n"}