{"black": "Batsiashvili,N", "white": "Dzagnidze,N", "winner": "White", "playedAt": "2016.02.18", "location": "Tehran IRI", "event": "Tehran WGP 2016", "moves": "pgn1.d4 d5 2.c4 e6 3.Nf3 Nf6 4.e3 Be7 5.Nbd2 O-O 6.b3 b6 7.Bb2 Bb7 8.cxd5 exd5\n9.Bd3 Nbd7 10.O-O Bd6 11.Ne5 Ne4 12.Rc1 Qe7 13.Nxd7 Qxd7 14.Nb1 Qe7\n15.Rc2 f5 16.g3 Rf6 17.Qc1 c6 18.Ba3 Bxa3 19.Qxa3 Qxa3 20.Nxa3 a5\n21.Rfc1 Kf8 22.Nb1 Ke7 23.f3 Ng5 24.Kf2 Kd7 25.Nc3 Ne6 26.Na4 Kc7 27.f4 Nd8\n28.Nc3 Kd6 29.Na4 Kc7 30.Nc3 Kd6 31.Ne2 Ba6 32.Bxa6 Rxa6 33.Ng1 Rf7\n34.Nf3 Rc7 35.h3 h5 36.Rg1 Raa7 37.g4 hxg4 38.hxg4 fxg4 39.Rxg4 Rf7\n40.Rc1 Rf6 41.Rcg1 Ne6 42.Ng5 Re7 43.Nxe6 Rfxe6 44.Rg6 Rxg6\n45.Rxg6+ Kd7 46.Kf3 Kc7 47.f5 Rf7 48.Kf4 Re7 49.a3 Re4+ 50.Kf3 Re7\n51.b4 axb4 52.axb4 Kb7 53.Kf4 Kc7 54.Rg3 Kb7 55.Rg6 Kc7 56.Kg5 Kb7\n57.Re6 Rc7 58.Kg6 Ka6 59.Re8 Kb5 60.Rg8 Re7 61.Rxg7 Rxe3 62.f6 Kxb4\n63.f7 Rf3 64.Rg8 c5 65.dxc5 bxc5 66.f8=Q Rxf8 67.Rxf8 c4 68.Kf5 c3\n69.Kf4 Kc4 70.Ke3 d4+ 71.Ke4 Kb3 72.Kd3 Kb2 73.Rb8+ Kc1 74.Rb7 1-0\n"}