{"black": "Harika,D", "white": "Batchimeg,Tuvshintugs", "winner": "Draw", "playedAt": "2013.06.19", "location": "Dilijan ARM", "event": "FIDE WGP Dilijan 2013", "moves": "pgn1.d4 e6 2.c4 d5 3.Nf3 Nf6 4.Nc3 Bb4 5.cxd5 exd5 6.Bg5 h6 7.Bh4 g5 8.Bg3 Ne4\n9.Rc1 h5 10.Qa4+ Nc6 11.Ne5 Bd7 12.Nxd7 Qxd7 13.f3 h4 14.Bf2 Nxf2\n15.Kxf2 g4 16.e3 g3+ 17.Ke1 gxh2 18.Rxh2 Rh6 19.Bb5 Qd6 20.Rh3 Kf8\n21.Bxc6 bxc6 22.a3 Bxc3+ 23.Rxc3 Kg7 24.Qc2 Re8 25.Qf5 Ree6 26.Kf1 Qe7\n27.Kf2 a5 28.Qf4 a4 29.b4 axb3 30.Rxb3 c5 31.Rb7 cxd4 32.Qxd4+ Kh7\n33.Rb8 Qf6 34.Qxd5 Rd6 35.Qe4+ Kg7 36.f4 Rd2+ 37.Kf3 Qa6 38.Qe5+ Rf6\n39.Qg5+ Rg6 40.Qe5+ Rf6 41.Qb5 Qxb5 42.Rxb5 Rg6 43.Rxh4 Rgxg2\n44.a4 Rdf2+ 45.Ke4 Ra2 46.a5 c6 47.Re5 Rg3 48.Kf5 Ra3 49.Rg4+ Rxg4\n50.Kxg4 Kg6 51.Kf3 Ra4 52.Rc5 Kg7 53.Kg4 Re4 54.Kf3 Ra4 55.e4 f6 56.e5 fxe5\n57.Rxe5 Kf6 58.Rc5 Ke7 59.Rxc6 Rxa5 60.Kg4 Kf7 61.f5 Ra1 1/2-1/2\n"}