{"black": "Eljanov,P", "white": "Inarkiev,E", "winner": "Black", "playedAt": "2010.05.17", "location": "Astrakhan RUS", "event": "6th FIDE Grand Prix (2008-9)", "moves": "pgn1.e4 c6 2.d4 d5 3.e5 Bf5 4.Nf3 e6 5.Be2 c5 6.Be3 Qb6 7.Nc3 Qxb2 8.Qb1 Qxb1+\n9.Rxb1 c4 10.Rxb7 Nc6 11.Kd2 Bb4 12.Rb1 Ba5 13.g4 Bxg4 14.Rxf7 Bxf3\n15.Rxf3 Nge7 16.Rg1 Rg8 17.Rh3 Nf5 18.Bg4 Ncxd4 19.Bxd4 Nxd4\n20.Kc1 Bxc3 21.Rxc3 Ke7 22.f4 g6 23.Rh3 Rg7 24.Kd2 Rf7 25.Rb1 Rd8 26.c3 Nc6\n27.Ke3 h5 28.Be2 Kf8 29.Rg3 Ne7 30.Rgg1 d4+ 31.cxd4 Nd5+ 32.Kd2 Nxf4\n33.Bxc4 Rxd4+ 34.Kc3 Rd8 35.Kb4 Kg7 36.Rgd1 Rc8 37.Bb3 Rb7+ 38.Ka5 Rc5+\n39.Ka6 Rf7 40.Rd6 Rxe5 41.Rbd1 Re2 42.Rd7 Rxh2 43.Kxa7 Rb2\n44.Rxf7+ Kxf7 45.Kb6 g5 46.Kc5 h4 47.Kb4 Nd5+ 48.Kc5 h3 49.Bxd5 exd5\n50.Kxd5 Re2 0-1\n"}