{"black": "Tomashevsky,E", "white": "Bacrot,E", "winner": "Draw", "playedAt": "2013.09.28", "location": "Elancourt FRA", "event": "FIDE GP Paris", "moves": "pgn1.e4 e5 2.Nf3 Nc6 3.Bb5 a6 4.Ba4 Nf6 5.O-O Be7 6.Re1 b5 7.Bb3 O-O\n8.a4 b4 9.d3 d6 10.Nbd2 Be6 11.Bxe6 fxe6 12.c3 d5 13.Qe2 Bc5 14.Nb3 Ba7\n15.Be3 Bxe3 16.Qxe3 bxc3 17.bxc3 Qd6 18.Nbd2 h6 19.d4 exd4 20.cxd4 Nxe4\n21.Nxe4 dxe4 22.Qxe4 Rf4 23.Qxe6+ Qxe6 24.Rxe6 Nxd4 25.Nxd4 Rxd4\n26.Rc6 Rad8 27.g3 R8d6 28.Rxc7 Rd1+ 29.Rxd1 Rxd1+ 30.Kg2 Rd4\n31.Rc8+ Kf7 32.Rc7+ Kg8 33.Rc8+ Kf7 34.Rc7+ Kg8 1/2-1/2\n"}