{"black": "Xu Yuhua", "white": "Dzagnidze,N", "winner": "White", "playedAt": "2011.02.28", "location": "Doha QAT", "event": "2009-10 FIDE Women's Grand Prix", "moves": "pgn1.d4 e6 2.c4 Nf6 3.Nc3 Bb4 4.Qc2 O-O 5.a3 Bxc3+ 6.Qxc3 d5 7.Bg5 dxc4\n8.Qxc4 b6 9.Rd1 Ba6 10.Qc2 Nbd7 11.e4 Bxf1 12.Kxf1 Qc8 13.Qc6 Qa6+\n14.Ne2 Rad8 15.f3 h6 16.Bh4 e5 17.Kf2 exd4 18.Rxd4 Ne5 19.Qc3 Rxd4\n20.Qxd4 Re8 21.Bxf6 gxf6 22.Nf4 Qc4 23.Qxc4 Nxc4 24.Rc1 b5 25.b3 Nxa3\n26.Rxc7 Ra8 27.b4 a5 28.bxa5 Rxa5 29.Nd5 Kg7 30.Rc6 Nc4 31.Nxf6 Ra2+\n32.Kg3 Ne3 33.Nh5+ Kh7 34.Nf4 b4 35.Rb6 Rb2 36.Rb7 Kg8 37.h4 b3\n38.h5 Kf8 39.Rb8+ Kg7 40.Rb7 Kf8 41.Kh3 Rb1 42.Nd3 Rh1+ 43.Kg3 Rxh5\n44.Kf2 Nc4 45.Rxb3 Ra5 46.Nf4 Ra2+ 47.Kg3 Kg7 48.Kh3 Ra3 49.Rb5 Ra5\n50.Rb7 Ra3 51.Rc7 Ne5 52.Ne6+ Kg6 53.Nd4 h5 54.Nf5 Ra2 55.Rc5 Nd3\n56.Nh4+ Kg7 57.Rg5+ Kh6 58.Rf5 Ra7 59.Kg3 Rd7 60.Rf6+ Kg7 61.Rb6 f6\n62.Nf5+ Kg6 63.Ne3 Rg7 64.Nd5 Rf7 65.Kh4 Ne5 66.Ra6 Rf8 67.Nf4+ Kh6\n68.Nxh5 Nd7 69.g4 Kg6 70.Rd6 Ne5 71.f4 1-0\n"}