{"black": "Harika,D", "white": "Zhao Xue", "winner": "White", "playedAt": "2013.09.30", "location": "Tashkent UZB", "event": "FIDE WGP Tashkent", "moves": "pgn1.d4 e6 2.c4 d5 3.Nc3 Nf6 4.Nf3 Be7 5.Bg5 h6 6.Bh4 O-O 7.e3 Ne4\n8.Bg3 Bb4 9.Qc2 c5 10.Bd3 cxd4 11.exd4 Nxg3 12.hxg3 dxc4 13.Bxc4 Nc6\n14.Rd1 Bd7 15.g4 Be7 16.a3 Rc8 17.Ba2 Re8 18.Bb1 f5 19.O-O Bf6 20.Rfe1 Ne7\n21.Qd3 Qb6 22.Rd2 Qd6 23.Ba2 fxg4 24.Ne4 Qf4 25.Ne5 Bxe5 26.dxe5 Rcd8\n27.Nc5 Bc8 28.Qxd8 Rxd8 29.Rxd8+ Kh7 30.Bb1+ g6 31.g3 Qc4 32.Ne4 Kg7\n33.Nd6 Qc6 34.Be4 Qc5 35.Re8 Qxe5 36.Rxe7+ Kf8 37.Nxc8 h5 38.Rd1 1-0\n"}